ado_ray_tune/__init__.py
ado_ray_tune/config.py
ado_ray_tune/doe.py
ado_ray_tune/operator.py
ado_ray_tune/operator_function.py
ado_ray_tune/rifferla.py
ado_ray_tune/rifferla_operation_debug.py
ado_ray_tune/samplers.py
ado_ray_tune/space_analysis.py
ado_ray_tune/stoppers.py
ado_ray_tune-1.4.1.dist-info/METADATA
ado_ray_tune-1.4.1.dist-info/WHEEL
ado_ray_tune-1.4.1.dist-info/entry_points.txt
ado_ray_tune-1.4.1.dist-info/top_level.txt
ado_ray_tune-1.4.1.dist-info/RECORD
