Metadata-Version: 2.4
Name: ado-ray-tune
Version: 1.4.1
Requires-Dist: ray[tune]>=2.9
Requires-Dist: bayesian-optimization>=1.4.0
Requires-Dist: nevergrad>=1.0.12
Requires-Dist: paretoset>=1.2.4
Requires-Dist: scipy>=1.15.3
